odoo/addons/mindev/README.rst
odoo/addons/mindev/__init__.py
odoo/addons/mindev/__manifest__.py
odoo/addons/mindev/models/__init__.py
odoo/addons/mindev/models/group.py
odoo/addons/mindev/models/menu.py
odoo/addons/mindev/models/tools_translate.py
odoo/addons/mindev/security/groups.xml
odoo/addons/mindev/static/description/icon.png
odoo/addons/mindev/views/delete_attachments_views.xml
odoo/addons/mindev/views/download_translations_view.xml
odoo/addons/mindev/views/group.xml
odoo/addons/mindev/views/menu.xml
odoo/addons/mindev/views/min_dev_menu.xml
odoo/addons/mindev/wizards/__init__.py
odoo/addons/mindev/wizards/delete_attachments.py
odoo/addons/mindev/wizards/download_translations.py
odoo12_addon_mindev-12.0.0.2.0.dist-info/LICENSE
odoo12_addon_mindev-12.0.0.2.0.dist-info/METADATA
odoo12_addon_mindev-12.0.0.2.0.dist-info/WHEEL
odoo12_addon_mindev-12.0.0.2.0.dist-info/top_level.txt
odoo12_addon_mindev-12.0.0.2.0.dist-info/RECORD
