Metadata-Version: 2.1
Name: odoo12-addon-mindev
Version: 12.0.0.2.0
Summary: Development Utilities
Home-page: https://www.minorisa.net
Author: Minorisa SA
License: GPL-3
Platform: UNKNOWN
Classifier: Programming Language :: Python
Classifier: Framework :: Odoo
Classifier: License :: OSI Approved :: GNU General Public License v3 (GPLv3)
Requires-Python: >=3.5
Requires-Dist: odoo (<12.1dev,>=12.0a)
